biotmed_dms_sdk/__init__.py
biotmed_dms_sdk/api_client.py
biotmed_dms_sdk/api_response.py
biotmed_dms_sdk/configuration.py
biotmed_dms_sdk/exceptions.py
biotmed_dms_sdk/py.typed
biotmed_dms_sdk/rest.py
biotmed_dms_sdk/api/__init__.py
biotmed_dms_sdk/api/analytics_db_connection_api_api.py
biotmed_dms_sdk/api/analytics_db_state_api_api.py
biotmed_dms_sdk/api/analytics_dbapi_api.py
biotmed_dms_sdk/api/bi_dashboard_api_api.py
biotmed_dms_sdk/api/health_check_api_api.py
biotmed_dms_sdk/api/report_api_api.py
biotmed_dms_sdk/api/temporary_token_operation_api_api.py
biotmed_dms_sdk/models/__init__.py
biotmed_dms_sdk/models/analytics_db_connection_details_response.py
biotmed_dms_sdk/models/analytics_db_information_response.py
biotmed_dms_sdk/models/create_report_request.py
biotmed_dms_sdk/models/error_response.py
biotmed_dms_sdk/models/filter_v2.py
biotmed_dms_sdk/models/metadata.py
biotmed_dms_sdk/models/order.py
biotmed_dms_sdk/models/page_metadata.py
biotmed_dms_sdk/models/report_file_output.py
biotmed_dms_sdk/models/report_initiator_response.py
biotmed_dms_sdk/models/report_locations.py
biotmed_dms_sdk/models/report_output_metadata.py
biotmed_dms_sdk/models/report_query.py
biotmed_dms_sdk/models/report_response.py
biotmed_dms_sdk/models/search_request_v2.py
biotmed_dms_sdk/models/search_response_report_response.py
biotmed_dms_sdk/models/token_operation_request.py
biotmed_dms_sdk/models/token_operation_response.py
biotmed_dms_sdk/models/version_response.py
biotmed_dms_sdk-2.3.40.dist-info/METADATA
biotmed_dms_sdk-2.3.40.dist-info/WHEEL
biotmed_dms_sdk-2.3.40.dist-info/top_level.txt
biotmed_dms_sdk-2.3.40.dist-info/RECORD
